kaas/cli.py
kaas/parser.py
kaas-0.0.2.dist-info/METADATA
kaas-0.0.2.dist-info/WHEEL
kaas-0.0.2.dist-info/entry_points.txt
kaas-0.0.2.dist-info/top_level.txt
kaas-0.0.2.dist-info/RECORD
