Metadata-Version: 2.1
Name: kaas
Version: 0.0.2
Summary: UNKNOWN
Home-page: https://github.com/DavidVentura/kaas
License: UNKNOWN
Platform: UNKNOWN
Classifier: Programming Language :: Python :: 3
Classifier: License :: OSI Approved :: MIT License
Classifier: Operating System :: OS Independent
Requires-Python: >=3.6
Requires-Dist: pyleri (==1.3.2)
